pyconfmanager.py
pyconfmanager-1.0.0.dist-info/WHEEL
pyconfmanager-1.0.0.dist-info/METADATA
pyconfmanager-1.0.0.dist-info/RECORD
