Metadata-Version: 2.1
Name: pyconfmanager
Version: 1.0.0
Summary: Simple lib to read configs
Author: Xenely
Requires-Python: >=3.8,<4.0
Classifier: Programming Language :: Python :: 3
Classifier: Programming Language :: Python :: 3.10
Classifier: Programming Language :: Python :: 3.8
Classifier: Programming Language :: Python :: 3.9
